em3u8/__init__.py
em3u8/cmd.py
em3u8/httpclient.py
em3u8/logger.py
em3u8/m3u8.py
em3u8/parse.py
em3u8/sites/__init__.py
em3u8/sites/site.py
em3u8/sites/yunbtv.py
vget-0.32.dist-info/METADATA
vget-0.32.dist-info/WHEEL
vget-0.32.dist-info/entry_points.txt
vget-0.32.dist-info/top_level.txt
vget-0.32.dist-info/RECORD
