Metadata-Version: 2.1
Name: vget
Version: 0.32
Summary: A simple tool with m3u8 resouce download package
Home-page: https://vget.readthedocs.io
Author: xiaotech
Author-email: xiaotech@163.com
License: Apache 2.0
Requires-Dist: loguru
Requires-Dist: requests
Requires-Dist: beautifulsoup4
Requires-Dist: tqdm
Requires-Dist: pycryptodome
Requires-Dist: click
